pydraw/__init__.py
pydraw/color.py
pydraw/compound.py
pydraw/errors.py
pydraw/location.py
pydraw/objects.py
pydraw/overload.py
pydraw/scene.py
pydraw/screen.py
pydraw/sound.py
pydraw/turtle.py
pydraw/util.py
tests/__init__.py
tests/algorithms_test.py
tests/blank_test.py
tests/color_test.py
tests/image_test.py
tests/input_test.py
tests/launcher.py
tests/line_test.py
tests/location_test.py
tests/objects_test.py
tests/overload_test.py
tests/polygon_test.py
tests/scene_test.py
tests/screen_test.py
tests/text_test.py
tests/tutorial.py
pydraw-2.2.1.dist-info/METADATA
pydraw-2.2.1.dist-info/WHEEL
pydraw-2.2.1.dist-info/top_level.txt
pydraw-2.2.1.dist-info/RECORD
