Metadata-Version: 2.4
Name: pydraw
Version: 2.2.1
Summary: A package designed to make graphics with Python simple and easy!
Home-page: https://github.com/pydraw/pydraw
Author: Noah Coetsee
Author-email: noah@noahcoetsee.me
License: MIT
Classifier: Programming Language :: Python :: 3
Classifier: License :: OSI Approved :: MIT License
Classifier: Operating System :: OS Independent
Requires-Python: >=3.6
Requires-Dist: pillow
Dynamic: author
Dynamic: author-email
Dynamic: classifier
Dynamic: description
Dynamic: description-content-type
Dynamic: home-page
Dynamic: license
Dynamic: requires-dist
Dynamic: requires-python
Dynamic: summary
